pylint_requests/__init__.py
pylint_requests/__pkginfo__.py
pylint_requests/checkers/__init__.py
pylint_requests/checkers/requests_installed.py
pylint_requests/checkers/timeout.py
pylint_requests/utils.py
pylint_requests-0.1.1.dist-info/LICENSE
pylint_requests-0.1.1.dist-info/WHEEL
pylint_requests-0.1.1.dist-info/METADATA
pylint_requests-0.1.1.dist-info/RECORD
