Metadata-Version: 2.1
Name: pylint-requests
Version: 0.1.1
Summary: A pylint plugin to check for common issues with usage of requests
Home-page: https://pypi.org/project/pylint-requests
License: MIT
Keywords: pylint,requests,timeout
Author: Mikhail Burshteyn
Author-email: mdburshteyn@gmail.com
Requires-Python: >=3.6,<4.0
Classifier: Development Status :: 3 - Alpha
Classifier: Environment :: Console
Classifier: Environment :: Plugins
Classifier: Intended Audience :: Developers
Classifier: License :: OSI Approved :: MIT License
Classifier: Programming Language :: Python :: 3
Classifier: Programming Language :: Python :: 3.6
Classifier: Programming Language :: Python :: 3.7
Classifier: Programming Language :: Python :: 3.8
Classifier: Topic :: Software Development :: Quality Assurance
Requires-Dist: pylint (>=2.0,<3.0)
Project-URL: Repository, https://github.com/m-burst/pylint-requests
